setup.py
hhcalcs/__init__.py
hhcalcs/hydraulics.py
hhcalcs.egg-info/PKG-INFO
hhcalcs.egg-info/SOURCES.txt
hhcalcs.egg-info/dependency_links.txt
hhcalcs.egg-info/not-zip-safe
hhcalcs.egg-info/top_level.txt