Metadata-Version: 1.0
Name: hhcalcs
Version: 0.1
Summary: Tools for common hydraulic and hydrologic engineering calculations
Home-page: https://github.com/aerispaha/hhcalcs
Author: Adam Erispaha
Author-email: aerispaha@gmail.com
License: MIT
Platform: UNKNOWN
